nr/__init__.py
nr/databind/__init__.py
nr/databind/json/__init__.py
nr/databind/json/decorations.py
nr/databind/json/serializers.py
nr.databind.json-0.0.14.dist-info/LICENSE.txt
nr.databind.json-0.0.14.dist-info/METADATA
nr.databind.json-0.0.14.dist-info/WHEEL
nr.databind.json-0.0.14.dist-info/top_level.txt
nr.databind.json-0.0.14.dist-info/zip-safe
nr.databind.json-0.0.14.dist-info/RECORD
