Metadata-Version: 2.1
Name: nr.databind.json
Version: 0.0.14
Summary: Deserialize JSON into Python objects and reverse.
Home-page: https://git.niklasrosenstein.com/NiklasRosenstein/nr
Author: Niklas Rosenstein
Author-email: rosensteinniklas@gmail.com
License: MIT
Platform: UNKNOWN
Requires-Dist: nr.collections (<1.0.0,>=0.0.1)
Requires-Dist: nr.databind.core (<0.1.0,>=0.0.21)
Requires-Dist: nr.interface (<0.1.0,>=0.0.1)
Requires-Dist: nr.parsing.date (<1.0.0,>=0.1.0)
Requires-Dist: nr.pylang.utils (<0.1.0,>=0.0.1)
